[
	{
		"titre": "vocabulaire 1",
		"description": "Description du vocabulaire 1",
		"helpText": "Texte d'aide",
		"etiquettes": false,
		"choixMultiple": true,
		"obligatoire": false,
		"id":"506441f8c64804fa13000000",
		"termes": {
			"children": [
				{
					"text": "terme1",
					"children": []
				}, {
					"text": "terme2",
					"children": [
						{
							"text": "terme3",
							"children": []
						}
					]
				}
			]
		}
	}, {
		"titre": "vocabulaire 2",
		"description": "Description du vocabulaire 2",
		"helpText": "Texte d'aide",
		"etiquettes": false,
		"choixMultiple": true,
		"obligatoire": false,
		"termes": {
			"children": []
		}
	}
]
